{
	"label": "Wizerunek szajki",
	"entries": {
		"Alluring": {
			"name": "Uwodzicielscy",
			"description": ""
		},
		"Ambitious": {
			"name": "Ambitni",
			"description": ""
		},
		"Brutal": {
			"name": "Brutalni",
			"description": ""
		},
		"Cruel": {
			"name": "Bezlitośni",
			"description": ""
		},
		"Daring": {
			"name": "Odważni",
			"description": ""
		},
		"Ferocious": {
			"name": "Dzicy",
			"description": ""
		},
		"Honorable": {
			"name": "Honorowi",
			"description": ""
		},
		"Monstrous": {
			"name": "Odpychający",
			"description": ""
		},
		"Professional": {
			"name": "Profesjonalni",
			"description": ""
		},
		"Radiant": {
			"name": "Światli",
			"description": ""
		},
		"Savvy": {
			"name": "Cwani",
			"description": ""
		},
		"Serene": {
			"name": "Opanowani",
			"description": ""
		},
		"Sinister": {
			"name": "Kasandryczni",
			"description": ""
		},
		"Strange": {
			"name": "Dziwni",
			"description": ""
		},
		"Subtle": {
			"name": "Subtelni",
			"description": ""
		},
		"Transcendent": {
			"name": "???",
			"description": ""
		}
	}
}